pandas_toon/__init__.py
pandas_toon/core.py
pandas_toon/io.py
pandas_toon/parser.py
pandas_toon/py.typed
pandas_toon-0.1.0.dist-info/licenses/LICENSE
pandas_toon-0.1.0.dist-info/METADATA
pandas_toon-0.1.0.dist-info/WHEEL
pandas_toon-0.1.0.dist-info/entry_points.txt
pandas_toon-0.1.0.dist-info/top_level.txt
pandas_toon-0.1.0.dist-info/RECORD
