Metadata-Version: 2.4
Name: pandas-toon
Version: 0.1.0
Summary: TOON (Token-Oriented Object Notation) format support for pandas
Author: pandas-toon contributors
License: Apache-2.0
Project-URL: Homepage, https://github.com/AMSeify/pandas-toon
Project-URL: Repository, https://github.com/AMSeify/pandas-toon
Project-URL: Documentation, https://github.com/AMSeify/pandas-toon#readme
Project-URL: Bug Tracker, https://github.com/AMSeify/pandas-toon/issues
Project-URL: Changelog, https://github.com/AMSeify/pandas-toon/blob/main/CHANGELOG.md
Keywords: pandas,toon,llm,data,serialization
Classifier: Development Status :: 3 - Alpha
Classifier: Intended Audience :: Developers
Classifier: License :: OSI Approved :: Apache Software License
Classifier: Programming Language :: Python :: 3
Classifier: Programming Language :: Python :: 3.8
Classifier: Programming Language :: Python :: 3.9
Classifier: Programming Language :: Python :: 3.10
Classifier: Programming Language :: Python :: 3.11
Classifier: Programming Language :: Python :: 3.12
Classifier: Topic :: Software Development :: Libraries :: Python Modules
Requires-Python: >=3.8
License-File: LICENSE
Requires-Dist: pandas>=1.3.0
Provides-Extra: dev
Requires-Dist: pytest>=7.0.0; extra == "dev"
Requires-Dist: pytest-cov>=4.0.0; extra == "dev"
Requires-Dist: ruff>=0.1.0; extra == "dev"
Requires-Dist: mypy>=1.0.0; extra == "dev"
Requires-Dist: build>=1.0.0; extra == "dev"
Requires-Dist: twine>=4.0.0; extra == "dev"
Dynamic: license-file
